BarkNotificator/__init__.py
BarkNotificator/barknotificator.py
BarkNotificator/exception.py
BarkNotificator/key.p8
barknotificator-0.2.0.dist-info/LICENSE
barknotificator-0.2.0.dist-info/METADATA
barknotificator-0.2.0.dist-info/WHEEL
barknotificator-0.2.0.dist-info/top_level.txt
barknotificator-0.2.0.dist-info/RECORD
